[
    {
        "path": "404.html",
        "type": "file",
        "md5": "0b9a0b7b5a4b543e6620342b60de795a"
    },
    {
        "path": "assets",
        "type": "directory",
        "md5": false
    },
    {
        "path": "assets/css",
        "type": "directory",
        "md5": false
    },
    {
        "path": "/assets/css/editor.css",
        "type": "file",
        "md5": "4202808df745f2ac7ab250606fa0d272"
    },
    {
        "path": "/assets/css/main.css",
        "type": "file",
        "md5": "fa238f48f9a2ab93b0c59a116e831bca"
    },
    {
        "path": "/assets/css/style.css",
        "type": "file",
        "md5": "11bee19e86e8eda2cf9a60efd975666d"
    },
    {
        "path": "assets/dynamic",
        "type": "directory",
        "md5": false
    },
    {
        "path": "assets/js",
        "type": "directory",
        "md5": false
    },
    {
        "path": "/assets/js/scripts.js",
        "type": "file",
        "md5": "e9e5c3efbaa696d1490988cf5b30e23b"
    },
    {
        "path": "/assets/js/scripts.min.js",
        "type": "file",
        "md5": "700105c316933a8202041b6415abb233"
    },
    {
        "path": "/assets/js/svg-fix.js",
        "type": "file",
        "md5": "9b7d020c55e2b4f77ab40c97f88f9ff4"
    },
    {
        "path": "/assets/js/svg-map.js",
        "type": "file",
        "md5": "ff4392540fcf4c3d3f5e03806e112816"
    },
    {
        "path": "assets/svg",
        "type": "directory",
        "md5": false
    },
    {
        "path": "/assets/svg/svg-map.svg",
        "type": "file",
        "md5": "cf04dfd5c3cc64e0be44692fe7d976a6"
    },
    {
        "path": "authors",
        "type": "directory",
        "md5": false
    },
    {
        "path": "authors/mrw",
        "type": "directory",
        "md5": false
    },
    {
        "path": "/authors/mrw/index.html",
        "type": "file",
        "md5": "4781fd7e464b1bc665a0e45cb83c5856"
    },
    {
        "path": "feed.json",
        "type": "file",
        "md5": "de46acf65079aaaa50e3c1a04dd49523"
    },
    {
        "path": "feed.xml",
        "type": "file",
        "md5": "06484b51f53f0e76def0854b405d5bdc"
    },
    {
        "path": "index.html",
        "type": "file",
        "md5": "1c75c574c0a21518bc941c5276e7106e"
    },
    {
        "path": "robots.txt",
        "type": "file",
        "md5": "d395396bcf9f873bf3ebd3067a2527ad"
    },
    {
        "path": "shrk-tnzyf-bjd-hlwl-mtkml-lnzf-htrfy-wbyy-shy-mryh.html",
        "type": "file",
        "md5": "5bd17bac25ec3e78247be7fa92ca254c"
    },
    {
        "path": "shrk-tnzyf-bjd-khdmt-htrfy-lnzf-shml-wbyy-shy.html",
        "type": "file",
        "md5": "7d32dad1562fb0a2211c878322f56c74"
    },
    {
        "path": "shrk-tnzyf-bjd-wkhdm-tnzyf-lsjd-blbkhr.html",
        "type": "file",
        "md5": "a741f1b6346c72745590c42c12ba798d"
    },
    {
        "path": "sitemap.xml",
        "type": "file",
        "md5": "2f4d979fdc7c214e1116ad20ba2adb1b"
    },
    {
        "path": "sitemap.xsl",
        "type": "file",
        "md5": "03c2f9a7fdcc46ff05c435907614a0b8"
    },
    {
        "path": "tags",
        "type": "directory",
        "md5": false
    },
    {
        "path": "/tags/index.html",
        "type": "file",
        "md5": "718ca840d59d77d1416104a3b343f799"
    }
]